README.md
setup.py
spikefeatures/__init__.py
spikefeatures/features.py
spikefeatures/version.py
spikefeatures.egg-info/PKG-INFO
spikefeatures.egg-info/SOURCES.txt
spikefeatures.egg-info/dependency_links.txt
spikefeatures.egg-info/requires.txt
spikefeatures.egg-info/top_level.txt
spikefeatures/tests/__init__.py
spikefeatures/tests/test_features.py
spikefeatures/tests/utils.py