Metadata-Version: 2.1
Name: spikefeatures
Version: 0.1.1
Summary: Python toolkit for computing extracellular waveforms features
Home-page: https://github.com/SpikeInterface/spikefeatures
Author: Alessio Buccino, Thijs Ruikes
Author-email: alessiop.buccino@gmail.com
License: UNKNOWN
Platform: UNKNOWN
Classifier: Programming Language :: Python :: 3
Classifier: License :: OSI Approved :: Apache Software License
Classifier: Operating System :: OS Independent
